ttopt/__init__.py
ttopt/maxvol.py
ttopt/ttopt.py
ttopt/ttopt_raw.py
ttopt-0.6.2.dist-info/LICENSE.txt
ttopt-0.6.2.dist-info/METADATA
ttopt-0.6.2.dist-info/WHEEL
ttopt-0.6.2.dist-info/top_level.txt
ttopt-0.6.2.dist-info/RECORD
