Metadata-Version: 2.1
Name: ttopt
Version: 0.6.2
Summary: Multivariate function optimizer based on the tensor train approach.
Home-page: https://github.com/AndreiChertkov/ttopt
Author: Andrei Chertkov
Author-email: andre.chertkov@gmail.com
Project-URL: Source, https://github.com/AndreiChertkov/ttopt
Keywords: function optimization function minimization low-rank representation tensor train format TT-decomposition cross approximation
Classifier: Development Status :: 4 - Beta
Classifier: License :: OSI Approved :: MIT License
Classifier: Topic :: Scientific/Engineering
Classifier: Topic :: Scientific/Engineering :: Mathematics
Classifier: Topic :: Scientific/Engineering :: Information Analysis
Classifier: Topic :: Scientific/Engineering :: Artificial Intelligence
Classifier: Intended Audience :: Science/Research
Classifier: Operating System :: OS Independent
Classifier: Programming Language :: Python :: 3
Classifier: Programming Language :: Python :: 3 :: Only
Classifier: Programming Language :: Python :: 3.7
Classifier: Programming Language :: Python :: 3.8
Classifier: Programming Language :: Python :: 3.9
Requires-Python: >=3.7
License-File: LICENSE.txt
Requires-Dist: numpy (<1.22) ; python_version == "3.7"
Requires-Dist: scipy (<1.8) ; python_version == "3.7"
Requires-Dist: numpy (<1.25,>=1.22) ; python_version == "3.8"
Requires-Dist: scipy (<1.11,>=1.9) ; python_version == "3.8"
Requires-Dist: numpy (>=1.22) ; python_version >= "3.9"
Requires-Dist: scipy (>=1.9) ; python_version >= "3.9"
